mrsensemakr/__init__.py
mrsensemakr/_version.py
mrsensemakr/mr_plots.py
mrsensemakr/mrsensemakr.py
mrsensemakr/traditional_mr.py
mrsensemakr-0.0.2.dist-info/METADATA
mrsensemakr-0.0.2.dist-info/WHEEL
mrsensemakr-0.0.2.dist-info/top_level.txt
mrsensemakr-0.0.2.dist-info/RECORD
