Metadata-Version: 2.1
Name: mrsensemakr
Version: 0.0.2
Summary: mrsensemakr: Python implementation of the mrsensemakr package
Home-page: https://github.com/nlapier2/mrsensemakr
Author: Nathan LaPierre
Author-email: nathanl2012@gmail.com
License: UNKNOWN
Platform: UNKNOWN
Classifier: Development Status :: 3 - Alpha
Classifier: Topic :: Scientific/Engineering :: Bio-Informatics
Classifier: Topic :: Scientific/Engineering :: Mathematics
Classifier: License :: OSI Approved :: MIT License
Classifier: Intended Audience :: Science/Research
Classifier: Programming Language :: Python :: 3.8
Classifier: Natural Language :: English
Classifier: Operating System :: MacOS :: MacOS X
Classifier: Operating System :: POSIX :: Linux
Requires-Python: >=3.8
Requires-Dist: pandas
Requires-Dist: numpy
Requires-Dist: statsmodels
Requires-Dist: matplotlib
Requires-Dist: scipy
Requires-Dist: jupyter
Requires-Dist: sphinx
Requires-Dist: sphinx-autobuild
Requires-Dist: Pysensemakr
